adi_notebook/__init__.py
adi_notebook/constant.py
adi_notebook/pcm_overview.py
adi_notebook/py.typed
adi_notebook/runner.py
adi_notebook-0.3.3.dist-info/METADATA
adi_notebook-0.3.3.dist-info/WHEEL
adi_notebook-0.3.3.dist-info/entry_points.txt
adi_notebook-0.3.3.dist-info/top_level.txt
adi_notebook-0.3.3.dist-info/RECORD
